anyrun/__init__.py
anyrun/client.py
anyrun/tests.py
anyrun-0.3.dist-info/LICENSE
anyrun-0.3.dist-info/METADATA
anyrun-0.3.dist-info/WHEEL
anyrun-0.3.dist-info/top_level.txt
anyrun-0.3.dist-info/RECORD
