Metadata-Version: 2.1
Name: anyrun
Version: 0.3
Summary: app.any.run malware submissions client
Home-page: https://github.com/mwalkowski/anyrun
Author: Michal Walkowski
Author-email: mi.walkowski@gmail.com
License: pache Software License 2.0
Keywords: malware submissions app.any.run
Platform: UNKNOWN
Classifier: Development Status :: 3 - Alpha
Classifier: Intended Audience :: Developers
Classifier: Natural Language :: English
Classifier: Programming Language :: Python :: 3
Classifier: Programming Language :: Python :: 3.5
Classifier: Programming Language :: Python :: 3.6
Classifier: Programming Language :: Python :: 3.7
Requires-Dist: websocket-client (==0.57.0)
Requires-Dist: pytest-runner (==5.2)
